easydata_distributions/Binomialdistribution.py
easydata_distributions/Gaussiandistribution.py
easydata_distributions/Generaldistribution.py
easydata_distributions/__init__.py
easydata_distributions-1.2.dist-info/METADATA
easydata_distributions-1.2.dist-info/WHEEL
easydata_distributions-1.2.dist-info/top_level.txt
easydata_distributions-1.2.dist-info/RECORD
