Metadata-Version: 2.1
Name: easydata-distributions
Version: 1.2
Summary: Gaussian and Binomial distributions
Home-page: UNKNOWN
Author: Sumit Paul
Author-email: sumit.18.paul@gmail.com
License: UNKNOWN
Platform: UNKNOWN
